Wx_sequential.v
// module multiplier_16_bit(in_a, in_b, out_c);

// input 	[15:0] in_a;
// input 	[15:0] in_b;
// output 	[15:0] out_c;

// reg [15:0] c;

// always @(in_a or in_b)
// begin
// 	c <= in_a * in_b;
// end

// assign out_c = c;

// endmodule


module Wx_sequential(in_clock, axis_s_tvalid, axis_m_tready, axis_s_tdata, axis_m_tdata, axis_m_tvalid, axis_s_tready);

input             in_clock;
input             axis_s_tvalid;
input 			  axis_m_tready;
input      [15:0] axis_s_tdata;
output 	   [47:0] axis_m_tdata;
output 			  axis_m_tvalid;
output 			  axis_s_tready;	

reg [48:0] r_a = 16'd0;
reg [48:0] r_b = 16'd0;
wire [47:0] ab;
wire [47:0] data;

reg [15:0] x = 16'd0;
reg [31:0] x2 = 32'd0;
reg [32:0] x2_mult_2 = 33'd0;
reg [47:0] x3 = 48'd0;

reg [2:0] counter = 3'd0;
reg data_valid = 1'b0;

always @(posedge in_clock)
begin

		if((counter > 16'd0) & (counter < 16'd4)) begin
			counter <= counter + 3'd1;
		end

		if((axis_s_tvalid == 1'b1) & (counter == 3'd0)) 
			x <= axis_s_tdata;
			counter <= counter + 3'd1;
		
		if (counter == 3'd1) begin
			r_a <= x;
			r_b <= x;
			x2 <= x * x;

		end else if (counter == 3'd2) begin
			r_a <= x2;
			r_b <= 48'd2;
			x2_mult_2 <= 2 * x2;

		end else if (counter == 3'd3) begin
			r_a <= x2;
			r_b <= x;
			x3 <= x2 * x;

		end else if (counter == 3'd4) begin
			data_valid <= 1'b1;
		end else if (counter == 3'd5) begin
			r_a <= 16'd0;
			r_b <= 16'd0;
			x2 <= 16'd0;
			x2_mult_2 <= 16'd0;
			x3 <= 16'd0;
			counter <= 3'd0;
			data_valid <= 1'b0;
		end
		
end

// multiplier_16_bit mult
//     (
// 		  .in_a(r_a),
// 		  .in_b(r_b),
// 	      .out_c(ab)
//     );

assign axis_m_tdata = x3 + x2_mult_2 + x + 16'd1;
assign axis_m_tvalid = ((data_valid == 1'b1) && (axis_m_tready == 1'b1)) ? 1'b1 :
						  1'b0;
assign axis_s_tready = (counter == 3'd0) ? 1'b1 :
					1'b0;
						 
endmodule

Wx_sequential_wrapper.v
module Wx_sequential_wrapper(in_clock, axis_s_tvalid, axis_m_tready, axis_s_tdata, axis_m_tdata, axis_m_tvalid, axis_s_tready);

output      reg    in_clock;
input             axis_s_tvalid;
input 			  axis_m_tready;
input   signed    [15:0] axis_s_tdata;
output 	signed    [47:0] axis_m_tdata;
output 			  axis_m_tvalid;
output 			  axis_s_tready;	
  Wx_sequential dut(
	  .in_clock(in_clock),
	  .axis_s_tvalid(axis_s_tvalid),
	  .axis_m_tready(axis_m_tready),
	  .axis_s_tdata(axis_s_tdata),
	  .axis_m_tdata(axis_m_tdata),
	  .axis_m_tvalid(axis_m_tvalid),
	  .axis_s_tready(axis_s_tready)
  );

  initial begin
	  $dumpfile("Wx_sequential.vcd");
	  $dumpvars;
	  in_clock=0;
	  forever begin
		  #5 in_clock=~in_clock;
	  end
  end
  endmodule

Wx_sequential.vcd
$date
	Wed Feb 22 07:17:42 2023
$end
$version
	Icarus Verilog
$end
$timescale
	1ps
$end
$scope module Wx_sequential_wrapper $end
$var wire 1 ! axis_m_tready $end
$var wire 16 " axis_s_tdata [15:0] $end
$var wire 1 # axis_s_tvalid $end
$var wire 1 $ axis_s_tready $end
$var wire 1 % axis_m_tvalid $end
$var wire 48 & axis_m_tdata [47:0] $end
$var reg 1 ' in_clock $end
$scope module dut $end
$var wire 1 ! axis_m_tready $end
$var wire 16 ( axis_s_tdata [15:0] $end
$var wire 1 # axis_s_tvalid $end
$var wire 1 ' in_clock $end
$var wire 1 $ axis_s_tready $end
$var wire 1 % axis_m_tvalid $end
$var wire 48 ) axis_m_tdata [47:0] $end
$var reg 3 * counter [2:0] $end
$var reg 1 + data_valid $end
$var reg 49 , r_a [48:0] $end
$var reg 49 - r_b [48:0] $end
$var reg 16 . x [15:0] $end
$var reg 32 / x2 [31:0] $end
$var reg 33 0 x2_mult_2 [32:0] $end
$var reg 48 1 x3 [47:0] $end
$upscope $end
$upscope $end
$enddefinitions $end
#0
$dumpvars
b0 1
b0 0
b0 /
b0 .
b0 -
b0 ,
0+
b1 *
b1 )
b0 (
1'
b1 &
0%
0$
0#
b0 "
1!
$end
#5000
1#
0'
#10000
b10 *
1'
#15000
0#
0'
#20000
b10 -
b11 *
1'
#25000
0'
#30000
b0 -
b100 *
1'
#35000
0'
#40000
1%
1+
b101 *
1'
#45000
0'
#50000
0%
1$
0+
b0 *
1'
#55000
b1010101 "
b1010101 (
1#
0'
#60000
0$
b1 *
b1010110 &
b1010110 )
b1010101 .
1'
#65000
b0 "
b0 (
0#
0'
#70000
b1110000111001 /
b1010101 -
b1010101 ,
b10 *
1'
#75000
0'
#80000
b11100011001000 &
b11100011001000 )
b11100001110010 0
b10 -
b1110000111001 ,
b11 *
1'
#85000
0'
#90000
b10011001011110110101 &
b10011001011110110101 )
b10010101111011101101 1
b1010101 -
b100 *
1'
#95000
0'
#100000
1%
1+
b101 *
1'
#105000
0'
#110000
0%
1$
0+
b0 1
b1010110 &
b1010110 )
b0 0
b0 /
b0 -
b0 ,
b0 *
1'
#115000
b10110110 "
b10110110 (
1#
0'
#120000
0$
b1 *
b10110111 &
b10110111 )
b10110110 .
1'
#125000
b0 "
b0 (
0#
0'
#130000
b1000000101100100 /
b10110110 -
b10110110 ,
b10 *
1'
#135000
0'
#140000
b10000001101111111 &
b10000001101111111 )
b10000001011001000 0
b10 -
b1000000101100100 ,
b11 *
1'
#145000
0'
#150000
b10111010000000010010111 &
b10111010000000010010111 )
b10110111111110100011000 1
b10110110 -
b100 *
1'
#155000
0'
#160000
1%
1+
b101 *
1'
#165000
0'
#170000
0%
1$
0+
b0 1
b10110111 &
b10110111 )
b0 0
b0 /
b0 -
b0 ,
b0 *
1'
#175000
b1000010 "
b1000010 (
1#
0'
#180000
0$
b1 *
b1000011 &
b1000011 )
b1000010 .
1'
#185000
b0 "
b0 (
0#
0'
#190000
b1000100000100 /
b1000010 -
b1000010 ,
b10 *
1'
#195000
0'
#200000
b10001001001011 &
b10001001001011 )
b10001000001000 0
b10 -
b1000100000100 ,
b11 *
1'
#205000
0'
#210000
b1001000010101010011 &
b1001000010101010011 )
b1000110001100001000 1
b1000010 -
b100 *
1'
#215000
0'
#220000
1%
1+
b101 *
1'
#225000
0'
#230000
0%
1$
0+
b0 1
b1000011 &
b1000011 )
b0 0
b0 /
b0 -
b0 ,
b0 *
1'
#235000
b10001 "
b10001 (
1#
0'
#240000
0$
b1 *
b10010 &
b10010 )
b10001 .
1'
#245000
b0 "
b0 (
0#
0'
#250000
b100100001 /
b10001 -
b10001 ,
b10 *
1'
#255000
0'
#260000
b1001010100 &
b1001010100 )
b1001000010 0
b10 -
b100100001 ,
b11 *
1'
#265000
0'
#270000
b1010110000101 &
b1010110000101 )
b1001100110001 1
b10001 -
b100 *
1'
#275000
0'
#280000
1%
1+
b101 *
1'
#285000
0'
#290000
0%
1$
0+
b0 1
b10010 &
b10010 )
b0 0
b0 /
b0 -
b0 ,
b0 *
1'
#295000
b111111 "
b111111 (
1#
0'
#300000
0$
b1 *
b1000000 &
b1000000 )
b111111 .
1'
#305000
b0 "
b0 (
0#
0'
#310000
b111110000001 /
b111111 -
b111111 ,
b10 *
1'
#315000
0'
#320000
b1111101000010 &
b1111101000010 )
b1111100000010 0
b10 -
b111110000001 ,
b11 *
1'
#325000
0'
#330000
b111111000000000001 &
b111111000000000001 )
b111101000010111111 1
b111111 -
b100 *
1'
#335000
0'
#340000
1%
1+
b101 *
1'
#345000
0'
#350000
0%
1$
0+
b0 1
b1000000 &
b1000000 )
b0 0
b0 /
b0 -
b0 ,
b0 *
1'
#355000
b1000101 "
b1000101 (
1#
0'
#360000
0$
b1 *
b1000110 &
b1000110 )
b1000101 .
1'
#365000
b0 "
b0 (
0#
0'
#370000
b1001010011001 /
b1000101 -
b1000101 ,
b10 *
1'
#375000
0'
#380000
b10010101111000 &
b10010101111000 )
b10010100110010 0
b10 -
b1001010011001 ,
b11 *
1'
#385000
0'
#390000
b1010010100010110101 &
b1010010100010110101 )
b1010000001100111101 1
b1000101 -
b100 *
1'
#395000
0'
#400000
1%
1+
b101 *
1'
#405000
0'
#410000
0%
1$
0+
b0 1
b1000110 &
b1000110 )
b0 0
b0 /
b0 -
b0 ,
b0 *
1'
#415000
b100000 "
b100000 (
1#
0'
#420000
0$
b1 *
b100001 &
b100001 )
b100000 .
1'
#425000
b0 "
b0 (
0#
0'
#430000
b10000000000 /
b100000 -
b100000 ,
b10 *
1'
#435000
0'
#440000
b100000100001 &
b100000100001 )
b100000000000 0
b10 -
b10000000000 ,
b11 *
1'
#445000
0'
#450000
b1000100000100001 &
b1000100000100001 )
b1000000000000000 1
b100000 -
b100 *
1'
#455000
0'
#460000
1%
1+
b101 *
1'
#465000
0'
#470000
0%
1$
0+
b0 1
b100001 &
b100001 )
b0 0
b0 /
b0 -
b0 ,
b0 *
1'
#475000
b10101 "
b10101 (
1#
0'
#480000
0$
b1 *
b10110 &
b10110 )
b10101 .
1'
#485000
b0 "
b0 (
0#
0'
#490000
b110111001 /
b10101 -
b10101 ,
b10 *
1'
#495000
0'
#500000
b1110001000 &
b1110001000 )
b1101110010 0
b10 -
b110111001 ,
b11 *
1'
#505000
0'
#510000
b10011110110101 &
b10011110110101 )
b10010000101101 1
b10101 -
b100 *
1'
#515000
0'
#520000
1%
1+
b101 *
1'
#525000
0'
#530000
0%
1$
0+
b0 1
b10110 &
b10110 )
b0 0
b0 /
b0 -
b0 ,
b0 *
1'
#535000
b10110101 "
b10110101 (
1#
0'
#540000
0$
b1 *
b10110110 &
b10110110 )
b10110101 .
1'
#545000
b0 "
b0 (
0#
0'
#550000
b111111111111001 /
b10110101 -
b10110101 ,
b10 *
1'
#555000
0'
#560000
b10000000010101000 &
b10000000010101000 )
b1111111111110010 0
b10 -
b111111111111001 ,
b11 *
1'
#565000
0'
#570000
b10110110111101110110101 &
b10110110111101110110101 )
b10110100111101100001101 1
b10110101 -
b100 *
1'
#575000
0'
#580000
1%
1+
b101 *
1'
#585000
0'
#590000
0%
1$
0+
b0 1
b10110110 &
b10110110 )
b0 0
b0 /
b0 -
b0 ,
b0 *
1'
