Wx_sequential.v
module Wx_sequential(in_clock, axis_s_tvalid, axis_m_tready, axis_s_tdata, axis_m_tdata, axis_m_tvalid, axis_s_tready);

input             in_clock;
input             axis_s_tvalid;
input 			  axis_m_tready;
input      [15:0] axis_s_tdata;
output 	   [47:0] axis_m_tdata;
output 			  axis_m_tvalid;
output 			  axis_s_tready;	

localparam X2 = 1;
localparam X22 = 2;
localparam X3 = 3;
localparam VALID = 4;
localparam RESTART = 5;


wire [48:0] r_a;
wire [48:0] r_b;

wire [47 : 0] result;


assign r_a = (counter == 3'd1) ? x :
			 ((counter == 3'd2) || (counter == 3'd3)) ? x2 :
			 48'd0;

assign r_b = ((counter == 3'd1) || (counter == 3'd3)) ? x :
			 ((counter == 3'd2)) ? 48'd2 :
			 48'd0;

assign result = r_a * r_b;


wire [47:0] ab;
wire [47:0] data;

reg [15:0] x = 16'd0;
reg [31:0] x2 = 32'd0;
reg [32:0] x2_mult_2 = 33'd0;
reg [47:0] x3 = 48'd0;

reg [2:0] counter = 3'd0;
reg data_valid = 1'b0;

always @(posedge in_clock)
begin

		if((counter > 16'd0) & (counter < 16'd4)) begin
			counter <= counter + 3'd1;
		end

		if((axis_s_tvalid == 1'b1) & (counter == 3'd0)) 
			x <= axis_s_tdata;
			counter <= counter + 3'd1;
		
		if (counter == X2) begin
			x2 <= result;

		end else if (counter == X22) begin
			x2_mult_2 <= result;

		end else if (counter == X3) begin
			x3 <= result;

		end else if (counter == VALID) begin
			data_valid <= 1'b1;
		end else if (counter == RESTART) begin
			x2 <= 16'd0;
			x2_mult_2 <= 16'd0;
			x3 <= 16'd0;
			counter <= 3'd0;
			data_valid <= 1'b0;
		end
		
end

assign axis_m_tdata = x3 + x2_mult_2 + x + 16'd1;
assign axis_m_tvalid = ((data_valid == 1'b1) && (axis_m_tready == 1'b1)) ? 1'b1 :
						  1'b0;
assign axis_s_tready = (counter == 3'd0) ? 1'b1 :
					1'b0;
						 
endmodule

Wx_sequential_wrapper.v
module Wx_sequential_wrapper(in_clock, axis_s_tvalid, axis_m_tready, axis_s_tdata, axis_m_tdata, axis_m_tvalid, axis_s_tready);

output      reg    in_clock;
input             axis_s_tvalid;
input 			  axis_m_tready;
input   signed    [15:0] axis_s_tdata;
output 	signed    [47:0] axis_m_tdata;
output 			  axis_m_tvalid;
output 			  axis_s_tready;	
  Wx_sequential dut(
	  .in_clock(in_clock),
	  .axis_s_tvalid(axis_s_tvalid),
	  .axis_m_tready(axis_m_tready),
	  .axis_s_tdata(axis_s_tdata),
	  .axis_m_tdata(axis_m_tdata),
	  .axis_m_tvalid(axis_m_tvalid),
	  .axis_s_tready(axis_s_tready)
  );

  initial begin
	  $dumpfile("Wx_sequential.vcd");
	  $dumpvars;
	  in_clock=0;
	  forever begin
		  #5 in_clock=~in_clock;
	  end
  end
  endmodule

Wx_sequential.vcd
$date
	Mon Feb 27 08:04:23 2023
$end
$version
	Icarus Verilog
$end
$timescale
	1ps
$end
$scope module Wx_sequential_wrapper $end
$var wire 1 ! axis_m_tready $end
$var wire 16 " axis_s_tdata [15:0] $end
$var wire 1 # axis_s_tvalid $end
$var wire 1 $ axis_s_tready $end
$var wire 1 % axis_m_tvalid $end
$var wire 48 & axis_m_tdata [47:0] $end
$var reg 1 ' in_clock $end
$scope module dut $end
$var wire 1 ! axis_m_tready $end
$var wire 16 ( axis_s_tdata [15:0] $end
$var wire 1 # axis_s_tvalid $end
$var wire 1 ' in_clock $end
$var wire 48 ) result [47:0] $end
$var wire 49 * r_b [48:0] $end
$var wire 49 + r_a [48:0] $end
$var wire 1 $ axis_s_tready $end
$var wire 1 % axis_m_tvalid $end
$var wire 48 , axis_m_tdata [47:0] $end
$var reg 3 - counter [2:0] $end
$var reg 1 . data_valid $end
$var reg 16 / x [15:0] $end
$var reg 32 0 x2 [31:0] $end
$var reg 33 1 x2_mult_2 [32:0] $end
$var reg 48 2 x3 [47:0] $end
$upscope $end
$upscope $end
$enddefinitions $end
#0
$dumpvars
b0 2
b0 1
b0 0
b0 /
0.
b1 -
b1 ,
b0 +
b0 *
b0 )
b0 (
1'
b1 &
0%
0$
0#
b0 "
1!
$end
#5000
1#
0'
#10000
b10 *
b10 -
1'
#15000
0#
0'
#20000
b0 *
b11 -
1'
#25000
0'
#30000
b100 -
1'
#35000
0'
#40000
1%
1.
b101 -
1'
#45000
0'
#50000
0%
1$
0.
b0 -
1'
#55000
b10111000 "
b10111000 (
1#
0'
#60000
b1000010001000000 )
b10111000 *
b10111000 +
0$
b1 -
b10111001 &
b10111001 ,
b10111000 /
1'
#65000
b0 "
b0 (
0#
0'
#70000
b10000100010000000 )
b10 *
b1000010001000000 +
b1000010001000000 0
b10 -
1'
#75000
0'
#80000
b10111110000111000000000 )
b10111000 *
b10000100100111001 &
b10000100100111001 ,
b10000100010000000 1
b11 -
1'
#85000
0'
#90000
b0 +
b0 )
b0 *
b11000000001011100111001 &
b11000000001011100111001 ,
b10111110000111000000000 2
b100 -
1'
#95000
0'
#100000
1%
1.
b101 -
1'
#105000
0'
#110000
0%
1$
0.
b0 2
b10111001 &
b10111001 ,
b0 1
b0 0
b0 -
1'
#115000
b1111101 "
b1111101 (
1#
0'
#120000
b11110100001001 )
b1111101 *
b1111101 +
0$
b1 -
b1111110 &
b1111110 ,
b1111101 /
1'
#125000
b0 "
b0 (
0#
0'
#130000
b111101000010010 )
b10 *
b11110100001001 +
b11110100001001 0
b10 -
1'
#135000
0'
#140000
b111011100110101100101 )
b1111101 *
b111101010010000 &
b111101010010000 ,
b111101000010010 1
b11 -
1'
#145000
0'
#150000
b0 +
b0 )
b0 *
b111100100011111110101 &
b111100100011111110101 ,
b111011100110101100101 2
b100 -
1'
#155000
0'
#160000
1%
1.
b101 -
1'
#165000
0'
#170000
0%
1$
0.
b0 2
b1111110 &
b1111110 ,
b0 1
b0 0
b0 -
1'
#175000
b10000110 "
b10000110 (
1#
0'
#180000
b100011000100100 )
b10000110 *
b10000110 +
0$
b1 -
b10000111 &
b10000111 ,
b10000110 /
1'
#185000
b0 "
b0 (
0#
0'
#190000
b1000110001001000 )
b10 *
b100011000100100 +
b100011000100100 0
b10 -
1'
#195000
0'
#200000
b1001001011011011011000 )
b10000110 *
b1000110011001111 &
b1000110011001111 ,
b1000110001001000 1
b11 -
1'
#205000
0'
#210000
b0 +
b0 )
b0 *
b1001010100001110100111 &
b1001010100001110100111 ,
b1001001011011011011000 2
b100 -
1'
#215000
0'
#220000
1%
1.
b101 -
1'
#225000
0'
#230000
0%
1$
0.
b0 2
b10000111 &
b10000111 ,
b0 1
b0 0
b0 -
1'
#235000
b1001000 "
b1001000 (
1#
0'
#240000
b1010001000000 )
b1001000 *
b1001000 +
0$
b1 -
b1001001 &
b1001001 ,
b1001000 /
1'
#245000
b0 "
b0 (
0#
0'
#250000
b10100010000000 )
b10 *
b1010001000000 +
b1010001000000 0
b10 -
1'
#255000
0'
#260000
b1011011001000000000 )
b1001000 *
b10100011001001 &
b10100011001001 ,
b10100010000000 1
b11 -
1'
#265000
0'
#270000
b0 +
b0 )
b0 *
b1011101101011001001 &
b1011101101011001001 ,
b1011011001000000000 2
b100 -
1'
#275000
0'
#280000
1%
1.
b101 -
1'
#285000
0'
#290000
0%
1$
0.
b0 2
b1001001 &
b1001001 ,
b0 1
b0 0
b0 -
1'
#295000
b1000 "
b1000 (
1#
0'
#300000
b1000000 )
b1000 *
b1000 +
0$
b1 -
b1001 &
b1001 ,
b1000 /
1'
#305000
b0 "
b0 (
0#
0'
#310000
b10000000 )
b10 *
b1000000 +
b1000000 0
b10 -
1'
#315000
0'
#320000
b1000000000 )
b1000 *
b10001001 &
b10001001 ,
b10000000 1
b11 -
1'
#325000
0'
#330000
b0 +
b0 )
b0 *
b1010001001 &
b1010001001 ,
b1000000000 2
b100 -
1'
#335000
0'
#340000
1%
1.
b101 -
1'
#345000
0'
#350000
0%
1$
0.
b0 2
b1001 &
b1001 ,
b0 1
b0 0
b0 -
1'
#355000
b111111 "
b111111 (
1#
0'
#360000
b111110000001 )
b111111 *
b111111 +
0$
b1 -
b1000000 &
b1000000 ,
b111111 /
1'
#365000
b0 "
b0 (
0#
0'
#370000
b1111100000010 )
b10 *
b111110000001 +
b111110000001 0
b10 -
1'
#375000
0'
#380000
b111101000010111111 )
b111111 *
b1111101000010 &
b1111101000010 ,
b1111100000010 1
b11 -
1'
#385000
0'
#390000
b0 +
b0 )
b0 *
b111111000000000001 &
b111111000000000001 ,
b111101000010111111 2
b100 -
1'
#395000
0'
#400000
1%
1.
b101 -
1'
#405000
0'
#410000
0%
1$
0.
b0 2
b1000000 &
b1000000 ,
b0 1
b0 0
b0 -
1'
#415000
b11000010 "
b11000010 (
1#
0'
#420000
b1001001100000100 )
b11000010 *
b11000010 +
0$
b1 -
b11000011 &
b11000011 ,
b11000010 /
1'
#425000
b0 "
b0 (
0#
0'
#430000
b10010011000001000 )
b10 *
b1001001100000100 +
b1001001100000100 0
b10 -
1'
#435000
0'
#440000
b11011110110100100001000 )
b11000010 *
b10010011011001011 &
b10010011011001011 ,
b10010011000001000 1
b11 -
1'
#445000
0'
#450000
b0 +
b0 )
b0 *
b11100001000111111010011 &
b11100001000111111010011 ,
b11011110110100100001000 2
b100 -
1'
#455000
0'
#460000
1%
1.
b101 -
1'
#465000
0'
#470000
0%
1$
0.
b0 2
b11000011 &
b11000011 ,
b0 1
b0 0
b0 -
1'
#475000
b1110100 "
b1110100 (
1#
0'
#480000
b11010010010000 )
b1110100 *
b1110100 +
0$
b1 -
b1110101 &
b1110101 ,
b1110100 /
1'
#485000
b0 "
b0 (
0#
0'
#490000
b110100100100000 )
b10 *
b11010010010000 +
b11010010010000 0
b10 -
1'
#495000
0'
#500000
b101111101000101000000 )
b1110100 *
b110100110010101 &
b110100110010101 ,
b110100100100000 1
b11 -
1'
#505000
0'
#510000
b0 +
b0 )
b0 *
b110000011101011010101 &
b110000011101011010101 ,
b101111101000101000000 2
b100 -
1'
#515000
0'
#520000
1%
1.
b101 -
1'
#525000
0'
#530000
0%
1$
0.
b0 2
b1110101 &
b1110101 ,
b0 1
b0 0
b0 -
1'
#535000
b1011101 "
b1011101 (
1#
0'
#540000
b10000111001001 )
b1011101 *
b1011101 +
0$
b1 -
b1011110 &
b1011110 ,
b1011101 /
1'
#545000
b0 "
b0 (
0#
0'
#550000
b100001110010010 )
b10 *
b10000111001001 +
b10000111001001 0
b10 -
1'
#555000
0'
#560000
b11000100011000000101 )
b1011101 *
b100001111110000 &
b100001111110000 ,
b100001110010010 1
b11 -
1'
#565000
0'
#570000
b0 +
b0 )
b0 *
b11001000100111110101 &
b11001000100111110101 ,
b11000100011000000101 2
b100 -
1'
#575000
0'
#580000
1%
1.
b101 -
1'
#585000
0'
#590000
0%
1$
0.
b0 2
b1011110 &
b1011110 ,
b0 1
b0 0
b0 -
1'
